haracat/__init__.py
haracat/download.py
haracat/normalizer.py
haracat/models/readme.txt
haracat-1.0.0.dist-info/METADATA
haracat-1.0.0.dist-info/RECORD
haracat-1.0.0.dist-info/WHEEL
haracat-1.0.0.dist-info/top_level.txt
