Metadata-Version: 2.1
Name: haracat
Version: 1.0.0
Summary: hAraCat 🐈 adds diacritics to Arabic text
Home-page: https://github.com/mikahama/haracat
Author: Mika Hämäläinen, Dept. of  Digital Humanities, University of Helsinki
Author-email: mika.hamalainen@helsinki.fi
License: Apache License, Version 2.0
Project-URL: Bug Reports, https://github.com/mikahama/haracat/issues
Project-URL: Developer, https://mikakalevi.com/
Keywords: Arabic,diacritic prediction,harakat
Platform: UNKNOWN
Classifier: Development Status :: 5 - Production/Stable
Classifier: Intended Audience :: Developers
Classifier: Topic :: Text Processing :: Linguistic
Classifier: Programming Language :: Python :: 3
Requires-Dist: natas
